{
  "development": {
    "username": "root",
    "password": "",
    "database": "kracknow",
    "host": "localhost",
    "dialect": "mysql",
    "operatorsAliases": false,
    "migrationStorageTableName": "sequelize_meta",
    "seederStorage": "sequelize",
    "seederStorageTableName": "sequelize_data"
  },
  "test": {
    "username": "root",
    "password": "",
    "database": "kracknow",
    "host": "localhost",
    "dialect": "mysql",
    "operatorsAliases": false,
    "migrationStorageTableName": "sequelize_meta",
    "seederStorage": "sequelize",
    "seederStorageTableName": "sequelize_data"
  },
  "production": {
   "username": "root",
    "password": "",
    "database": "kracknow",
    "host": "localhost",
    "dialect": "mysql",
    "operatorsAliases": false,
    "migrationStorageTableName": "sequelize_meta",
    "seederStorage": "sequelize",
    "seederStorageTableName": "sequelize_data"
  }
}